catlolzer/__init__.py
catlolzer/_version.py
catlolzer/core.py
catlolzer-0.0.1.dist-info/METADATA
catlolzer-0.0.1.dist-info/RECORD
catlolzer-0.0.1.dist-info/WHEEL
catlolzer-0.0.1.dist-info/top_level.txt
tests/__init__.py
tests/test_basics.py
